{"nodes": [{"id": "api_index_page", "label": "API reference index", "file_type": "document", "source_file": "frontend/apps/qeetid-docs/content/docs/api/index.mdx", "source_location": null, "source_url": null, "captured_at": null, "author": null, "contributor": null}, {"id": "api_index_base_url_residency", "label": "Residency-routed base URLs (US/EU/APAC)", "file_type": "concept", "source_file": "frontend/apps/qeetid-docs/content/docs/api/index.mdx", "source_location": null, "source_url": null, "captured_at": null, "author": null, "contributor": null}, {"id": "api_index_bearer_token_auth", "label": "Bearer token authentication", "file_type": "concept", "source_file": "frontend/apps/qeetid-docs/content/docs/api/index.mdx", "source_location": null, "source_url": null, "captured_at": null, "author": null, "contributor": null}, {"id": "api_index_key_types", "label": "Three key types (secret/publishable/PAT)", "file_type": "concept", "source_file": "frontend/apps/qeetid-docs/content/docs/api/index.mdx", "source_location": null, "source_url": null, "captured_at": null, "author": null, "contributor": null}, {"id": "api_index_versioning", "label": "URL + header versioning (90-day Sunset)", "file_type": "concept", "source_file": "frontend/apps/qeetid-docs/content/docs/api/index.mdx", "source_location": null, "source_url": null, "captured_at": null, "author": null, "contributor": null}, {"id": "api_index_openapi_spec", "label": "Public OpenAPI spec endpoint", "file_type": "concept", "source_file": "frontend/apps/qeetid-docs/content/docs/api/index.mdx", "source_location": null, "source_url": null, "captured_at": null, "author": null, "contributor": null}], "edges": [{"source": "api_index_page", "target": "api_index_base_url_residency", "relation": "references", "confidence": "EXTRACTED", "confidence_score": 1.0, "source_file": "frontend/apps/qeetid-docs/content/docs/api/index.mdx", "source_location": null, "weight": 1.0}, {"source": "api_index_page", "target": "api_index_bearer_token_auth", "relation": "references", "confidence": "EXTRACTED", "confidence_score": 1.0, "source_file": "frontend/apps/qeetid-docs/content/docs/api/index.mdx", "source_location": null, "weight": 1.0}, {"source": "api_index_page", "target": "api_index_key_types", "relation": "references", "confidence": "EXTRACTED", "confidence_score": 1.0, "source_file": "frontend/apps/qeetid-docs/content/docs/api/index.mdx", "source_location": null, "weight": 1.0}, {"source": "api_index_page", "target": "api_index_versioning", "relation": "references", "confidence": "EXTRACTED", "confidence_score": 1.0, "source_file": "frontend/apps/qeetid-docs/content/docs/api/index.mdx", "source_location": null, "weight": 1.0}, {"source": "api_index_page", "target": "api_index_openapi_spec", "relation": "references", "confidence": "EXTRACTED", "confidence_score": 1.0, "source_file": "frontend/apps/qeetid-docs/content/docs/api/index.mdx", "source_location": null, "weight": 1.0}, {"source": "api_index_page", "target": "api_errors_page", "relation": "references", "confidence": "EXTRACTED", "confidence_score": 1.0, "source_file": "frontend/apps/qeetid-docs/content/docs/api/index.mdx", "source_location": null, "weight": 1.0}, {"source": "api_index_page", "target": "api_pagination_page", "relation": "references", "confidence": "EXTRACTED", "confidence_score": 1.0, "source_file": "frontend/apps/qeetid-docs/content/docs/api/index.mdx", "source_location": null, "weight": 1.0}, {"source": "api_index_base_url_residency", "target": "docs_multi_tenancy_residency", "relation": "conceptually_related_to", "confidence": "EXTRACTED", "confidence_score": 1.0, "source_file": "frontend/apps/qeetid-docs/content/docs/api/index.mdx", "source_location": null, "weight": 1.0}], "hyperedges": []}